networking_utils/timestamp.py
networking_utils-0.1.6.dist-info/licenses/LICENSE
networking_utils-0.1.6.dist-info/METADATA
networking_utils-0.1.6.dist-info/WHEEL
networking_utils-0.1.6.dist-info/entry_points.txt
networking_utils-0.1.6.dist-info/top_level.txt
networking_utils-0.1.6.dist-info/RECORD
