Metadata-Version: 2.4
Name: networking-utils
Version: 0.1.6
Summary: A small collection of networking-related utility helpers (demo).
Author-email: Your Name <you@example.com>
License: MIT
Project-URL: Homepage, https://example.com/networking-utils
Project-URL: Repository, https://example.com/networking-utils/repo
Project-URL: Issues, https://example.com/networking-utils/issues
Keywords: networking,utilities,demo
Classifier: Programming Language :: Python :: 3
Classifier: Programming Language :: Python :: 3 :: Only
Classifier: Programming Language :: Python :: 3.8
Classifier: Programming Language :: Python :: 3.9
Classifier: Programming Language :: Python :: 3.10
Classifier: Programming Language :: Python :: 3.11
Classifier: Programming Language :: Python :: 3.12
Classifier: License :: OSI Approved :: MIT License
Classifier: Operating System :: OS Independent
Requires-Python: >=3.8
License-File: LICENSE
Provides-Extra: dev
Requires-Dist: pytest<9.0,>=7.0; extra == "dev"
Dynamic: license-file
